oidc/__init__.py
oidc/oid_client.py
oidc/oid_client_imp.py
oidc/realm.py
oidc/realm_imp.py
keycloak_oid_client-0.0.1.dist-info/METADATA
keycloak_oid_client-0.0.1.dist-info/WHEEL
keycloak_oid_client-0.0.1.dist-info/top_level.txt
keycloak_oid_client-0.0.1.dist-info/RECORD
